retrofor_wut/__init__.py
retrofor_wut/bot.py
retrofor_wut/config.py
retrofor_wut/event.py
retrofor_wut/exceptions.py
retrofor_wut/log.py
retrofor_wut/message.py
retrofor_wut/plugin.py
retrofor_wut/typing.py
retrofor_wut/utils.py
retrofor_wut/adapter/__init__.py
retrofor_wut/adapter/http_server_test_adapter.py
retrofor_wut/adapter/test.py
retrofor_wut/adapter/utils.py
retrofor_wut/adapter/apscheduler/__init__.py
retrofor_wut/adapter/apscheduler/config.py
retrofor_wut/adapter/apscheduler/event.py
retrofor_wut/adapter/cqhttp/__init__.py
retrofor_wut/adapter/cqhttp/config.py
retrofor_wut/adapter/cqhttp/event.py
retrofor_wut/adapter/cqhttp/exceptions.py
retrofor_wut/adapter/cqhttp/message.py
retrofor_wut/adapter/dingtalk/__init__.py
retrofor_wut/adapter/dingtalk/config.py
retrofor_wut/adapter/dingtalk/event.py
retrofor_wut/adapter/dingtalk/exceptions.py
retrofor_wut/adapter/dingtalk/message.py
retrofor_wut/adapter/mirai/__init__.py
retrofor_wut/adapter/mirai/config.py
retrofor_wut/adapter/mirai/exceptions.py
retrofor_wut/adapter/mirai/message.py
retrofor_wut/adapter/mirai/event/__init__.py
retrofor_wut/adapter/mirai/event/base.py
retrofor_wut/adapter/mirai/event/mate.py
retrofor_wut/adapter/mirai/event/message.py
retrofor_wut/adapter/mirai/event/notice.py
retrofor_wut/adapter/mirai/event/request.py
retrofor_wut-4.0.2.dist-info/LICENSE
retrofor_wut-4.0.2.dist-info/METADATA
retrofor_wut-4.0.2.dist-info/WHEEL
retrofor_wut-4.0.2.dist-info/top_level.txt
retrofor_wut-4.0.2.dist-info/RECORD
