Metadata-Version: 2.1
Name: retrofor-wut
Version: 4.0.2
Summary: Cross-platform robot framework, mainly used for machine learning.
Home-page: https://github.com/retrofor/retrofor_wut
Author: 简律纯
Author-email: HsiangNianian@outlook.com
License: MIT
Classifier: Development Status :: 3 - Alpha
Classifier: Framework :: AsyncIO
Classifier: Framework :: Robot Framework
Classifier: Framework :: Robot Framework :: Library
Classifier: Environment :: Console
Classifier: License :: OSI Approved :: MIT License
Classifier: Programming Language :: Python :: 3
Classifier: Topic :: Software Development :: Code Generators
Classifier: Topic :: Communications :: Chat
Requires-Python: >=3.8
License-File: LICENSE
Requires-Dist: flask
Requires-Dist: pydantic
Requires-Dist: loguru
Requires-Dist: aiohttp
Requires-Dist: tomli
Requires-Dist: typing-extensions
Requires-Dist: watchfiles
